chainsolvers/__init__.py
chainsolvers/helpers.py
chainsolvers/io.py
chainsolvers/locations.py
chainsolvers/run.py
chainsolvers/scoring_selection.py
chainsolvers/types.py
chainsolvers/visualizer.py
chainsolvers/solvers/__init__.py
chainsolvers/solvers/carla.py
chainsolvers/solvers/carla_plus.py
chainsolvers-0.1.0.dist-info/METADATA
chainsolvers-0.1.0.dist-info/WHEEL
chainsolvers-0.1.0.dist-info/top_level.txt
chainsolvers-0.1.0.dist-info/RECORD
