Metadata-Version: 2.4
Name: chainsolvers
Version: 0.1.0
Summary: Solvers for placing points along chains
License-Expression: MIT
Classifier: Development Status :: 4 - Beta
Classifier: Programming Language :: Python :: 3
Requires-Python: >=3.9
Requires-Dist: numpy
Requires-Dist: pandas
Requires-Dist: frozendict
Requires-Dist: scipy
Provides-Extra: viz
Requires-Dist: folium; extra == "viz"
Requires-Dist: networkx; extra == "viz"
Requires-Dist: pyproj; extra == "viz"
Requires-Dist: matplotlib; extra == "viz"
